dalla_data_processing/__init__.py
dalla_data_processing/_version.py
dalla_data_processing/cli.py
dalla_data_processing/core/README.md
dalla_data_processing/core/__init__.py
dalla_data_processing/core/dataset.py
dalla_data_processing/core/parallel.py
dalla_data_processing/deduplication/README.md
dalla_data_processing/deduplication/__init__.py
dalla_data_processing/deduplication/onion_wrapper.py
dalla_data_processing/deduplication/postprocessing.py
dalla_data_processing/deduplication/preprocessing.py
dalla_data_processing/deduplication/bin/.gitignore
dalla_data_processing/deduplication/bin/onion-darwin-universal
dalla_data_processing/deduplication/bin/onion-linux-x86_64
dalla_data_processing/deduplication/onion/COPYING
dalla_data_processing/deduplication/onion/Makefile
dalla_data_processing/deduplication/onion/Makefile.config
dalla_data_processing/deduplication/onion/README.md
dalla_data_processing/deduplication/onion/src/Makefile
dalla_data_processing/deduplication/onion/src/Makefile.g
dalla_data_processing/deduplication/onion/src/buzhash.c
dalla_data_processing/deduplication/onion/src/buzhash.h
dalla_data_processing/deduplication/onion/src/hashdup.c
dalla_data_processing/deduplication/onion/src/hashgen.c
dalla_data_processing/deduplication/onion/src/onion
dalla_data_processing/deduplication/onion/src/onion.c
dalla_data_processing/deduplication/onion/src/onion_dup.c
dalla_data_processing/deduplication/onion/src/version.c
dalla_data_processing/deduplication/onion/src/version.h
dalla_data_processing/deduplication/onion/src_sc/.gitignore
dalla_data_processing/deduplication/onion/src_sc/Makefile
dalla_data_processing/deduplication/onion/src_sc/Makefile.g
dalla_data_processing/deduplication/onion/src_sc/buzhash.c
dalla_data_processing/deduplication/onion/src_sc/buzhash.h
dalla_data_processing/deduplication/onion/src_sc/hashdup
dalla_data_processing/deduplication/onion/src_sc/hashdup.c
dalla_data_processing/deduplication/onion/src_sc/hashgen
dalla_data_processing-0.0.11.dist-info/licenses/LICENSE
dalla_data_processing-0.0.11.dist-info/METADATA
dalla_data_processing-0.0.11.dist-info/WHEEL
dalla_data_processing-0.0.11.dist-info/entry_points.txt
dalla_data_processing-0.0.11.dist-info/top_level.txt
dalla_data_processing-0.0.11.dist-info/RECORD
