Metadata-Version: 2.4
Name: dalla-data-processing
Version: 0.0.11
Summary: data processing pipeline with deduplication, stemming, quality checking, and readability scoring, used for the DALLA Models
Author-email: Hadi Hamoud <hhamoud@dohainstitute.edu.qa>, Digital Research Unit - Arab Center <dru@dohainstitute.edu.qa>
License: CC-BY-NC-SA-4.0
Project-URL: Homepage, https://github.com/U4RASD/dalla-data-processing
Project-URL: Documentation, https://github.com/U4RASD/dalla-data-processing#readme
Project-URL: Repository, https://github.com/U4RASD/dalla-data-processing
Project-URL: Bug Tracker, https://github.com/U4RASD/dalla-data-processing/issues
Keywords: arabic,nlp,data-processing,deduplication,stemming,readability,quality
Classifier: Intended Audience :: Developers
Classifier: Intended Audience :: Science/Research
Classifier: Programming Language :: Python :: 3
Classifier: Programming Language :: Python :: 3.10
Classifier: Programming Language :: Python :: 3.11
Classifier: Programming Language :: Python :: 3.12
Classifier: Programming Language :: Python :: 3.13
Classifier: Topic :: Scientific/Engineering :: Artificial Intelligence
Classifier: Topic :: Text Processing :: Linguistic
Requires-Python: >=3.10
License-File: LICENSE
Requires-Dist: datasets>=2.14.0
Requires-Dist: transformers>=4.30.0
Requires-Dist: click>=8.0.0
Requires-Dist: tqdm>=4.65.0
Requires-Dist: pyarrow>=12.0.0
Requires-Dist: structlog>=24.0.0
Provides-Extra: dev
Requires-Dist: pytest>=7.0.0; extra == "dev"
Requires-Dist: pytest-cov>=4.0.0; extra == "dev"
Requires-Dist: ruff>=0.1.0; extra == "dev"
Requires-Dist: pre-commit>=3.0.0; extra == "dev"
Provides-Extra: dedup
Requires-Dist: camel-tools==1.5.7; extra == "dedup"
Provides-Extra: dedup-native
Requires-Dist: cffi>=1.15.0; extra == "dedup-native"
Provides-Extra: stem
Requires-Dist: camel-tools==1.5.7; extra == "stem"
Provides-Extra: quality
Requires-Dist: camel-tools==1.5.7; extra == "quality"
Provides-Extra: readability
Requires-Dist: textstat>=0.7.0; extra == "readability"
Provides-Extra: pack
Requires-Dist: sentencepiece>=0.2.0; extra == "pack"
Requires-Dist: pyyaml; extra == "pack"
Provides-Extra: all
Requires-Dist: dalla-data-processing[dedup,dedup-native,dev,pack,quality,readability,stem]; extra == "all"
Dynamic: license-file
